mcp_monday/__init__.py
mcp_monday/monday-dev.py
mcp_monday/server.py
mcp_monday/tools.py
mcp_monday-0.1.0.dist-info/METADATA
mcp_monday-0.1.0.dist-info/WHEEL
mcp_monday-0.1.0.dist-info/entry_points.txt
mcp_monday-0.1.0.dist-info/RECORD
