Metadata-Version: 2.4
Name: mcp-monday
Version: 0.1.0
Summary: MCP Server for monday.com
Author-email: Jovan Sakovic <49978945+sakce@users.noreply.github.com>
Requires-Python: >=3.10
Requires-Dist: mcp>=1.2.1
Requires-Dist: monday>=2.0.1
Requires-Dist: requests>=2.32.3
Requires-Dist: ruff>=0.9.6
